Metadata-Version: 2.4
Name: material_fingerprinting_beta
Version: 0.1.4
Summary: A shortcut to material model discovery without solving optimization problems.
Home-page: https://github.com/Material-Fingerprinting
Author: Moritz Flaschel
Author-email: moritz.flaschel@fau.de
Requires-Python: >=3.10
License-File: LICENSE
Requires-Dist: matplotlib
Requires-Dist: numpy
Dynamic: author
Dynamic: author-email
Dynamic: description
Dynamic: description-content-type
Dynamic: home-page
Dynamic: license-file
Dynamic: requires-dist
Dynamic: requires-python
Dynamic: summary
